icu/.dylibs/libicudata.78.2.dylib
icu/.dylibs/libicui18n.78.2.dylib
icu/.dylibs/libicuuc.78.2.dylib
icu/__init__.py
icu/_icu_.cpython-39-darwin.so
icukit_pyicu-78.2.1.dist-info/METADATA
icukit_pyicu-78.2.1.dist-info/RECORD
icukit_pyicu-78.2.1.dist-info/WHEEL
icukit_pyicu-78.2.1.dist-info/entry_points.txt
icukit_pyicu-78.2.1.dist-info/licenses/LICENSE
icukit_pyicu-78.2.1.dist-info/top_level.txt
icukit_pyicu/__init__.py
icukit_pyicu/__main__.py
icukit_pyicu/bin/derb
icukit_pyicu/bin/genbrk
icukit_pyicu/bin/gencfu
icukit_pyicu/bin/gencnval
icukit_pyicu/bin/gendict
icukit_pyicu/bin/genrb
icukit_pyicu/bin/icu-config
icukit_pyicu/bin/icuexportdata
icukit_pyicu/bin/icuinfo
icukit_pyicu/bin/makeconv
icukit_pyicu/bin/pkgdata
icukit_pyicu/bin/uconv
icukit_pyicu/include/unicode/alphaindex.h
icukit_pyicu/include/unicode/appendable.h
icukit_pyicu/include/unicode/basictz.h
icukit_pyicu/include/unicode/brkiter.h
icukit_pyicu/include/unicode/bytestream.h
icukit_pyicu/include/unicode/bytestrie.h
icukit_pyicu/include/unicode/bytestriebuilder.h
icukit_pyicu/include/unicode/calendar.h
icukit_pyicu/include/unicode/caniter.h
icukit_pyicu/include/unicode/casemap.h
icukit_pyicu/include/unicode/char16ptr.h
icukit_pyicu/include/unicode/chariter.h
icukit_pyicu/include/unicode/choicfmt.h
icukit_pyicu/include/unicode/coleitr.h
icukit_pyicu/include/unicode/coll.h
icukit_pyicu/include/unicode/compactdecimalformat.h
icukit_pyicu/include/unicode/curramt.h
icukit_pyicu/include/unicode/currpinf.h
icukit_pyicu/include/unicode/currunit.h
icukit_pyicu/include/unicode/datefmt.h
icukit_pyicu/include/unicode/dbbi.h
icukit_pyicu/include/unicode/dcfmtsym.h
icukit_pyicu/include/unicode/decimfmt.h
icukit_pyicu/include/unicode/displayoptions.h
icukit_pyicu/include/unicode/docmain.h
icukit_pyicu/include/unicode/dtfmtsym.h
icukit_pyicu/include/unicode/dtintrv.h
icukit_pyicu/include/unicode/dtitvfmt.h
icukit_pyicu/include/unicode/dtitvinf.h
icukit_pyicu/include/unicode/dtptngen.h
icukit_pyicu/include/unicode/dtrule.h
icukit_pyicu/include/unicode/edits.h
icukit_pyicu/include/unicode/enumset.h
icukit_pyicu/include/unicode/errorcode.h
icukit_pyicu/include/unicode/fieldpos.h
icukit_pyicu/include/unicode/filteredbrk.h
icukit_pyicu/include/unicode/fmtable.h
