Metadata-Version: 2.1
Name: icukit-pyicu
Version: 78.2.1
Summary: Bundled ICU and PyICU for pip
Author: Kevin A. Lenzo
Author-email: keinlenzo@gmail.com
License: MIT
Project-URL: Homepage, https://github.com/lenzo-ka/icukit-pyicu
Keywords: icu,unicode,i18n,pyicu
Classifier: Development Status :: 5 - Production/Stable
Classifier: Intended Audience :: Developers
Classifier: License :: OSI Approved :: MIT License
Classifier: Operating System :: MacOS
Classifier: Operating System :: POSIX :: Linux
Classifier: Programming Language :: Python :: 3
Requires-Python: >=3.9
